testKuldeep.py
testKuldeep-0.0.8.dist-info/LICENCE.txt
testKuldeep-0.0.8.dist-info/METADATA
testKuldeep-0.0.8.dist-info/WHEEL
testKuldeep-0.0.8.dist-info/top_level.txt
testKuldeep-0.0.8.dist-info/RECORD
