Metadata-Version: 2.1
Name: testKuldeep
Version: 0.0.8
Summary: testing databricks
Author: Kuldeep Rathore
Keywords: python,databricks
Classifier: Programming Language :: Python :: 3
Classifier: License :: OSI Approved :: MIT License
Classifier: Operating System :: OS Independent
Requires-Python: >=3.6
License-File: LICENCE.txt
Requires-Dist: pyspark
Requires-Dist: DButils
